inputgooglesheets/__init__.py
inputgooglesheets/admin.py
inputgooglesheets/apps.py
inputgooglesheets/credentials.py
inputgooglesheets/exceptions.py
inputgooglesheets/forms.py
inputgooglesheets/importservice.py
inputgooglesheets/lock.py
inputgooglesheets/models.py
inputgooglesheets/spreadsheetservice.py
inputgooglesheets/tasks.py
inputgooglesheets/urls.py
inputgooglesheets/utils.py
inputgooglesheets/views.py
inputgooglesheets/management/__init__.py
inputgooglesheets/management/commands/__init__.py
inputgooglesheets/management/commands/autoimport_googlesheets.py
inputgooglesheets/migrations/0001_initial.py
inputgooglesheets/migrations/0002_auto_20191025_1516.py
inputgooglesheets/migrations/0003_spreadsheet_automatically_imported.py
inputgooglesheets/migrations/0004_settings_autoimport_sleep.py
inputgooglesheets/migrations/0005_auto_20200722_0222.py
inputgooglesheets/migrations/__init__.py
inputgooglesheets/static/css/inputgooglesheets.css
inputgooglesheets/static/js/inputgooglesheets.js
inputgooglesheets/templates/inputgooglesheets/base.html
dj_input_googlesheets-0.2.8.dist-info/AUTHORS.rst
dj_input_googlesheets-0.2.8.dist-info/LICENSE
dj_input_googlesheets-0.2.8.dist-info/METADATA
dj_input_googlesheets-0.2.8.dist-info/WHEEL
dj_input_googlesheets-0.2.8.dist-info/top_level.txt
dj_input_googlesheets-0.2.8.dist-info/RECORD
