Metadata-Version: 2.1
Name: dj-input-googlesheets
Version: 0.2.8
Summary: Input rows from google sheets into input-flow
Home-page: https://github.com/kverdecia/dj-input-googlesheets
Author: Karel Antonio Verdecia Ortiz
Author-email: kverdecia@gmail.com
License: UNKNOWN
Keywords: dj-input-googlesheets
Platform: UNKNOWN
Classifier: Development Status :: 3 - Alpha
Classifier: Framework :: Django :: 1.11
Classifier: Framework :: Django :: 2.0
Classifier: Intended Audience :: Developers
Classifier: License :: OSI Approved :: BSD License
Classifier: Natural Language :: English
Classifier: Programming Language :: Python :: 2
Classifier: Programming Language :: Python :: 2.7
Classifier: Programming Language :: Python :: 3
Classifier: Programming Language :: Python :: 3.4
Classifier: Programming Language :: Python :: 3.5
Classifier: Programming Language :: Python :: 3.6
License-File: LICENSE
License-File: AUTHORS.rst
Requires-Dist: requests
Requires-Dist: dj-oauth-clients (>=0.1.5)
Requires-Dist: dj-input-flow
Requires-Dist: pygsheets
Requires-Dist: python-redis-lock (>=3.3.1)
